openapi2jsonschema2/__init__.py
openapi2jsonschema2/command.py
openapi2jsonschema2/errors.py
openapi2jsonschema2/log.py
openapi2jsonschema2/util.py
openapi2jsonschema2-1.1.36.dist-info/METADATA
openapi2jsonschema2-1.1.36.dist-info/WHEEL
openapi2jsonschema2-1.1.36.dist-info/entry_points.txt
openapi2jsonschema2-1.1.36.dist-info/licenses/LICENSE
openapi2jsonschema2-1.1.36.dist-info/RECORD
