Metadata-Version: 2.4
Name: openapi2jsonschema2
Version: 1.1.36
Summary: A utility to extract JSON Schema from a valid OpenAPI specification
License-Expression: MIT
License-File: LICENSE
Keywords: openapi,jsonschema,kubeconform
Author: Gareth Rushgrove
Author-email: gareth@morethanseven.net
Requires-Python: >=3.10
Classifier: Programming Language :: Python :: 3
Classifier: Programming Language :: Python :: 3.10
Classifier: Programming Language :: Python :: 3.11
Classifier: Programming Language :: Python :: 3.12
Classifier: Programming Language :: Python :: 3.13
Classifier: Programming Language :: Python :: 3.14
Requires-Dist: click (>=8.0.0,<9.0.0)
Requires-Dist: jsonref (>=1.1.0,<2.0.0)
Requires-Dist: pyyaml (>=6.0.2,<7.0.0)
